blackboxai/__init__.py
blackboxai/__main__.py
blackboxai/__version__.py
blackboxai/analytics.py
blackboxai/app.py
blackboxai/args.py
blackboxai/args_formatter.py
blackboxai/commands.py
blackboxai/constants.py
blackboxai/diffs.py
blackboxai/dump.py
blackboxai/format_settings.py
blackboxai/gui.py
blackboxai/help.py
blackboxai/help_pats.py
blackboxai/history.py
blackboxai/io.py
blackboxai/linter.py
blackboxai/llm.py
blackboxai/main.py
blackboxai/mdstream.py
blackboxai/models.py
blackboxai/prompts.py
blackboxai/repo.py
blackboxai/repomap.py
blackboxai/report.py
blackboxai/run_cmd.py
blackboxai/scrape.py
blackboxai/search.py
blackboxai/sendchat.py
blackboxai/session.py
blackboxai/session_manager.py
blackboxai/special.py
blackboxai/urls.py
blackboxai/utils.py
blackboxai/versioncheck.py
blackboxai/voice.py
blackboxai/coders/__init__.py
blackboxai/coders/architect_coder.py
blackboxai/coders/architect_prompts.py
blackboxai/coders/ask_coder.py
blackboxai/coders/ask_prompts.py
blackboxai/coders/base_coder.py
blackboxai/coders/base_prompts.py
blackboxai/coders/chat_chunks.py
blackboxai/coders/editblock_coder.py
blackboxai/coders/editblock_fenced_coder.py
blackboxai/coders/editblock_fenced_prompts.py
blackboxai/coders/editblock_func_coder.py
blackboxai/coders/editblock_func_prompts.py
blackboxai/coders/editblock_prompts.py
blackboxai/coders/editor_editblock_coder.py
blackboxai/coders/editor_editblock_prompts.py
blackboxai/coders/editor_whole_coder.py
blackboxai/coders/editor_whole_prompts.py
blackboxai/coders/help_coder.py
blackboxai/coders/help_prompts.py
blackboxai/coders/search_replace.py
blackboxai/coders/single_wholefile_func_coder.py
blackboxai/coders/single_wholefile_func_prompts.py
blackboxai/coders/udiff_coder.py
blackboxai/coders/udiff_prompts.py
blackboxai/coders/wholefile_coder.py
blackboxai/coders/wholefile_func_coder.py
blackboxai/coders/wholefile_func_prompts.py
blackboxai/coders/wholefile_prompts.py
blackboxai/queries/README.md
blackboxai_chat-0.1.1.dist-info/LICENSE.txt
blackboxai_chat-0.1.1.dist-info/METADATA
blackboxai_chat-0.1.1.dist-info/WHEEL
blackboxai_chat-0.1.1.dist-info/entry_points.txt
blackboxai_chat-0.1.1.dist-info/top_level.txt
blackboxai_chat-0.1.1.dist-info/RECORD
